pc_rasterize/__init__.py
pc_rasterize/_version.py
pc_rasterize-0.2.0.dist-info/LICENSE
pc_rasterize-0.2.0.dist-info/METADATA
pc_rasterize-0.2.0.dist-info/WHEEL
pc_rasterize-0.2.0.dist-info/top_level.txt
pc_rasterize-0.2.0.dist-info/RECORD
