Metadata-Version: 2.1
Name: pc_rasterize
Version: 0.2.0
Summary: Rasterize point cloud data in parallel
Author-email: Fred Bunt <fredrick.bunt@umt.edu>
License: MIT License
Project-URL: homepage, https://github.com/UM-RMRS/pc-rasterize
Project-URL: issue-tracker, https://github.com/UM-RMRS/pc-rasterize/issues
Keywords: point,cloud,raster,spatial
Classifier: License :: OSI Approved :: MIT License
Classifier: Operating System :: OS Independent
Classifier: Programming Language :: Python
Classifier: Programming Language :: Python :: 3
Classifier: Topic :: Scientific/Engineering :: GIS
Requires-Python: >=3.10
License-File: LICENSE
Requires-Dist: dask
Requires-Dist: geopandas
Requires-Dist: numba
Requires-Dist: numpy
Requires-Dist: odc-geo
Requires-Dist: pandas
Requires-Dist: pdal
Requires-Dist: python-pdal
Requires-Dist: rasterio
Requires-Dist: rioxarray
Requires-Dist: shapely >=2
Requires-Dist: xarray
